<?xml version="1.0" encoding="utf-8"?>
<!--/804164/1186202/2.50/8/2/Integrated Circuit/-->
<quadcept_library>
  <setting unit="mil" />
  <textstyle name="Default" height="47.244094488189" strokewidth="7.8740157480315" charwidth="47.244094488189" />
  <textstyle name="Dimension" height="19.6850393700787" strokewidth="0" charwidth="19.6850393700787" />
  <textstyle name="H127W0635TH00762" height="50" strokewidth="3" charwidth="25" />
  <textstyle name="H15W15TH02" height="59.0551181102362" strokewidth="7.8740157480315" charwidth="59.0551181102362" />
  <padstyle name="r165_65" surface="True" plated="False" isvia="False" nopaste="False" nomask="True" complex="False" holesize="0">
    <padshape layer="TOP" shape="rectangle" width="25.590551181102" height="64.960629921259" />
    <padshape layer="TOP_SOLDER_MASK" shape="rectangle" width="33.464566929133" height="72.83464566929" />
    <padshape layer="TOP_SOLDER_PASTE" shape="rectangle" width="25.590551181102" height="64.960629921259" />
  </padstyle>
  <footprint name="SOIC127P790X216-8N" originx="0" originy="0" pickpointx="0" pickpointy="0">
    <pcbpin number="1" name="1" style="r165_65" originx="-141.73228346457" originy="74.999999999999" rotation="90" />
    <pcbpin number="2" name="2" style="r165_65" originx="-141.73228346457" originy="25" rotation="90" />
    <pcbpin number="3" name="3" style="r165_65" originx="-141.73228346457" originy="-25" rotation="90" />
    <pcbpin number="4" name="4" style="r165_65" originx="-141.73228346457" originy="-74.999999999999" rotation="90" />
    <pcbpin number="5" name="5" style="r165_65" originx="141.73228346457" originy="-74.999999999999" rotation="90" />
    <pcbpin number="6" name="6" style="r165_65" originx="141.73228346457" originy="-25" rotation="90" />
    <pcbpin number="7" name="7" style="r165_65" originx="141.73228346457" originy="25" rotation="90" />
    <pcbpin number="8" name="8" style="r165_65" originx="141.73228346457" originy="74.999999999999" rotation="90" />
    <line layer="TOP_PLACE_BOUND" originx="-184.05511811023" originy="114.76377952756" endx="184.05511811023" endy="114.76377952756" width="1.9685039370079" />
    <line layer="TOP_PLACE_BOUND" originx="184.05511811023" originy="114.76377952756" endx="184.05511811023" endy="-114.76377952756" width="1.9685039370079" />
    <line layer="TOP_PLACE_BOUND" originx="184.05511811023" originy="-114.76377952756" endx="-184.05511811023" endy="-114.76377952756" width="1.9685039370079" />
    <line layer="TOP_PLACE_BOUND" originx="-184.05511811023" originy="-114.76377952756" endx="-184.05511811023" endy="114.76377952756" width="1.9685039370079" />
    <line layer="TOP_ASSEMBLY" originx="-102.95275590551" originy="102.95275590551" endx="102.95275590551" endy="102.95275590551" width="3.9370078740157" />
    <line layer="TOP_ASSEMBLY" originx="102.95275590551" originy="102.95275590551" endx="102.95275590551" endy="-102.95275590551" width="3.9370078740157" />
    <line layer="TOP_ASSEMBLY" originx="102.95275590551" originy="-102.95275590551" endx="-102.95275590551" endy="-102.95275590551" width="3.9370078740157" />
    <line layer="TOP_ASSEMBLY" originx="-102.95275590551" originy="-102.95275590551" endx="-102.95275590551" endy="102.95275590551" width="3.9370078740157" />
    <line layer="TOP_ASSEMBLY" originx="-102.95275590551" originy="52.952755905511" endx="-52.952755905511" endy="102.95275590551" width="3.9370078740157" />
    <line layer="TOP_SILKSCREEN" originx="-95.472440944881" originy="102.95275590551" endx="95.472440944881" endy="102.95275590551" width="7.8740157480314" />
    <line layer="TOP_SILKSCREEN" originx="95.472440944881" originy="102.95275590551" endx="95.472440944881" endy="-102.95275590551" width="7.8740157480314" />
    <line layer="TOP_SILKSCREEN" originx="95.472440944881" originy="-102.95275590551" endx="-95.472440944881" endy="-102.95275590551" width="7.8740157480314" />
    <line layer="TOP_SILKSCREEN" originx="-95.472440944881" originy="-102.95275590551" endx="-95.472440944881" endy="102.95275590551" width="7.8740157480314" />
    <line layer="TOP_SILKSCREEN" originx="-174.21259842519" originy="101.57480314961" endx="-109.25196850394" endy="101.57480314961" width="7.8740157480314" />
  </footprint>
  <symbol name="W25Q128JVSIQ" originx="0" originy="0">
    <line originx="200" originy="100" endx="2000" endy="100" width="0" />
    <line originx="2000" originy="-400" endx="2000" endy="100" width="0" />
    <line originx="2000" originy="-400" endx="200" endy="-400" width="0" />
    <line originx="200" originy="100" endx="200" endy="-400" width="0" />
    <sympin number="1" originx="200" originy="0" rotation="180" length="100" width="7.8740157480315" flipped="False">
      <text name="pinname" originx="230" originy="0" style="Default" rotation="0" justify="left" flipped="False" hidden="False" data="/CS" />
      <text name="pindes" originx="140" originy="20" style="Default" rotation="0" justify="lowerright" flipped="False" hidden="False" data="1" />
    </sympin>
    <sympin number="2" originx="200" originy="-100" rotation="180" length="100" width="7.8740157480315" flipped="False">
      <text name="pinname" originx="230" originy="-100" style="Default" rotation="0" justify="left" flipped="False" hidden="False" data="DO_(IO1)" />
      <text name="pindes" originx="140" originy="-80" style="Default" rotation="0" justify="lowerright" flipped="False" hidden="False" data="2" />
    </sympin>
    <sympin number="3" originx="200" originy="-200" rotation="180" length="100" width="7.8740157480315" flipped="False">
      <text name="pinname" originx="230" originy="-200" style="Default" rotation="0" justify="left" flipped="False" hidden="False" data="/WP_(IO2)" />
      <text name="pindes" originx="140" originy="-180" style="Default" rotation="0" justify="lowerright" flipped="False" hidden="False" data="3" />
    </sympin>
    <sympin number="4" originx="200" originy="-300" rotation="180" length="100" width="7.8740157480315" flipped="False">
      <text name="pinname" originx="230" originy="-300" style="Default" rotation="0" justify="left" flipped="False" hidden="False" data="GND" />
      <text name="pindes" originx="140" originy="-280" style="Default" rotation="0" justify="lowerright" flipped="False" hidden="False" data="4" />
    </sympin>
    <sympin number="8" originx="2000" originy="0" rotation="0" length="100" width="7.8740157480315" flipped="False">
      <text name="pinname" originx="1970" originy="0" style="Default" rotation="0" justify="right" flipped="False" hidden="False" data="VCC" />
      <text name="pindes" originx="2060" originy="20" style="Default" rotation="0" justify="lowerleft" flipped="False" hidden="False" data="8" />
    </sympin>
    <sympin number="7" originx="2000" originy="-100" rotation="0" length="100" width="7.8740157480315" flipped="False">
      <text name="pinname" originx="1970" originy="-100" style="Default" rotation="0" justify="right" flipped="False" hidden="False" data="/HOLD_OR_/RESET_(IO3)" />
      <text name="pindes" originx="2060" originy="-80" style="Default" rotation="0" justify="lowerleft" flipped="False" hidden="False" data="7" />
    </sympin>
    <sympin number="6" originx="2000" originy="-200" rotation="0" length="100" width="7.8740157480315" flipped="False">
      <text name="pinname" originx="1970" originy="-200" style="Default" rotation="0" justify="right" flipped="False" hidden="False" data="CLK" />
      <text name="pindes" originx="2060" originy="-180" style="Default" rotation="0" justify="lowerleft" flipped="False" hidden="False" data="6" />
    </sympin>
    <sympin number="5" originx="2000" originy="-300" rotation="0" length="100" width="7.8740157480315" flipped="False">
      <text name="pinname" originx="1970" originy="-300" style="Default" rotation="0" justify="right" flipped="False" hidden="False" data="DI_(IO0)" />
      <text name="pindes" originx="2060" originy="-280" style="Default" rotation="0" justify="lowerleft" flipped="False" hidden="False" data="5" />
    </sympin>
  </symbol>
  <component name="W25Q128JVSIQ" designatorprefix="IC" height="85.039370078739" footprint="SOIC127P790X216-8N">
    <comppin designator="1" sympin="1" pinswap="0" gateswap="0" gate="1" group="1" side="" type="Any" name="/CS" />
    <comppin designator="2" sympin="2" pinswap="0" gateswap="0" gate="1" group="1" side="" type="Any" name="DO_(IO1)" />
    <comppin designator="3" sympin="3" pinswap="0" gateswap="0" gate="1" group="1" side="" type="Any" name="/WP_(IO2)" />
    <comppin designator="4" sympin="4" pinswap="0" gateswap="0" gate="1" group="1" side="" type="Any" name="GND" />
    <comppin designator="5" sympin="5" pinswap="0" gateswap="0" gate="1" group="1" side="" type="Any" name="DI_(IO0)" />
    <comppin designator="6" sympin="6" pinswap="0" gateswap="0" gate="1" group="1" side="" type="Any" name="CLK" />
    <comppin designator="7" sympin="7" pinswap="0" gateswap="0" gate="1" group="1" side="" type="Any" name="/HOLD_OR_/RESET_(IO3)" />
    <comppin designator="8" sympin="8" pinswap="0" gateswap="0" gate="1" group="1" side="" type="Any" name="VCC" />
    <attached_symbol gate="1" name="W25Q128JVSIQ" />
    <pinmap designator="1" footprintpin="1" />
    <pinmap designator="2" footprintpin="2" />
    <pinmap designator="3" footprintpin="3" />
    <pinmap designator="4" footprintpin="4" />
    <pinmap designator="5" footprintpin="5" />
    <pinmap designator="6" footprintpin="6" />
    <pinmap designator="7" footprintpin="7" />
    <pinmap designator="8" footprintpin="8" />
    <text name="Datasheet" originx="0" originy="0" style="Default" rotation="0" justify="" flipped="False" hidden="True" data="https://www.winbond.com/hq/search-resource-file.jsp?partNo=W25Q128JVSIQ&amp;type=datasheet" />
    <text name="Description" originx="0" originy="0" style="Default" rotation="0" justify="" flipped="False" hidden="True" data="128M-bit Serial Flash Memory with uniform 4KB sectors and Dual/Quad SPI" />
    <text name="Manufacturer_Name" originx="0" originy="0" style="Default" rotation="0" justify="" flipped="False" hidden="True" data="Winbond" />
    <text name="Manufacturer_Part_Number" originx="2050" originy="200" style="Default" rotation="0" justify="left" flipped="False" hidden="False" data="W25Q128JVSIQ" />
    <text name="Mouser Part Number" originx="0" originy="0" style="Default" rotation="0" justify="" flipped="False" hidden="True" data="454-W25Q128JVSIQ" />
    <text name="Mouser Price/Stock" originx="0" originy="0" style="Default" rotation="0" justify="" flipped="False" hidden="True" data="https://www.mouser.co.uk/ProductDetail/Winbond/W25Q128JVSIQ?qs=qSfuJ%252Bfl%2Fd6tLXvPR4fl9w%3D%3D" />
    <text name="Arrow Part Number" originx="0" originy="0" style="Default" rotation="0" justify="" flipped="False" hidden="True" data="W25Q128JVSIQ" />
    <text name="Arrow Price/Stock" originx="0" originy="0" style="Default" rotation="0" justify="" flipped="False" hidden="True" data="https://www.arrow.com/en/products/w25q128jvsiq/winbond-electronics?region=nac" />
  </component>
</quadcept_library>
